[
  {
    "idCarton": 981,
    "carton": [
      [
        null,
        18,
        24,
        null,
        44,
        null,
        66,
        null,
        null
      ],
      [
        8,
        null,
        28,
        32,
        null,
        52,
        null,
        null,
        86
      ],
      [
        9,
        null,
        null,
        null,
        49,
        59,
        68,
        80,
        null
      ]
    ]
  },
  {
    "idCarton": 982,
    "carton": [
      [
        null,
        15,
        27,
        null,
        null,
        null,
        63,
        75,
        null
      ],
      [
        3,
        null,
        null,
        null,
        47,
        58,
        null,
        null,
        90
      ],
      [
        4,
        null,
        null,
        37,
        null,
        null,
        null,
        null,
        null
      ]
    ]
  },
  {
    "idCarton": 983,
    "carton": [
      [
        null,
        15,
        null,
        35,
        null,
        56,
        null,
        75,
        null
      ],
      [
        10,
        19,
        29,
        null,
        null,
        null,
        null,
        null,
        85
      ],
      [
        null,
        null,
        null,
        null,
        48,
        null,
        68,
        80,
        90
      ]
    ]
  },
  {
    "idCarton": 984,
    "carton": [
      [
        null,
        11,
        null,
        null,
        null,
        58,
        null,
        null,
        null
      ],
      [
        null,
        null,
        23,
        34,
        41,
        null,
        63,
        74,
        82
      ],
      [
        6,
        null,
        null,
        null,
        42,
        null,
        70,
        null,
        85
      ]
    ]
  },
  {
    "idCarton": 985,
    "carton": [
      [
        10,
        15,
        26,
        null,
        41,
        55,
        null,
        null,
        null
      ],
      [
        null,
        17,
        null,
        null,
        null,
        57,
        68,
        71,
        null
      ],
      [
        null,
        null,
        null,
        31,
        45,
        null,
        69,
        null,
        85
      ]
    ]
  },
  {
    "idCarton": 986,
    "carton": [
      [
        1,
        12,
        null,
        null,
        null,
        56,
        null,
        null,
        null
      ],
      [
        null,
        null,
        22,
        null,
        41,
        57,
        62,
        72,
        84
      ],
      [
        9,
        null,
        28,
        38,
        45,
        null,
        64,
        73,
        null
      ]
    ]
  },
  {
    "idCarton": 987,
    "carton": [
      [
        null,
        null,
        24,
        null,
        null,
        58,
        null,
        75,
        82
      ],
      [
        6,
        16,
        null,
        null,
        46,
        null,
        65,
        78,
        null
      ],
      [
        null,
        null,
        null,
        35,
        50,
        null,
        67,
        null,
        null
      ]
    ]
  },
  {
    "idCarton": 988,
    "carton": [
      [
        4,
        null,
        null,
        null,
        41,
        null,
        null,
        79,
        84
      ],
      [
        null,
        11,
        25,
        null,
        47,
        53,
        61,
        null,
        null
      ],
      [
        null,
        18,
        null,
        36,
        null,
        null,
        null,
        80,
        null
      ]
    ]
  },
  {
    "idCarton": 989,
    "carton": [
      [
        null,
        null,
        null,
        34,
        44,
        null,
        67,
        null,
        89
      ],
      [
        null,
        20,
        25,
        null,
        45,
        null,
        null,
        71,
        null
      ],
      [
        2,
        null,
        null,
        null,
        null,
        60,
        null,
        73,
        null
      ]
    ]
  },
  {
    "idCarton": 990,
    "carton": [
      [
        null,
        null,
        24,
        32,
        46,
        51,
        null,
        79,
        null
      ],
      [
        10,
        14,
        null,
        null,
        null,
        null,
        null,
        80,
        83
      ],
      [
        null,
        18,
        null,
        34,
        null,
        null,
        61,
        null,
        null
      ]
    ]
  }
]