[
  {
    "idCarton": 1111,
    "carton": [
      [
        null,
        13,
        25,
        35,
        null,
        null,
        65,
        null,
        null
      ],
      [
        7,
        null,
        29,
        null,
        45,
        null,
        null,
        78,
        81
      ],
      [
        null,
        17,
        null,
        null,
        null,
        57,
        68,
        null,
        85
      ]
    ]
  },
  {
    "idCarton": 1112,
    "carton": [
      [
        null,
        14,
        null,
        32,
        null,
        60,
        62,
        75,
        null
      ],
      [
        1,
        null,
        22,
        null,
        43,
        null,
        null,
        null,
        86
      ],
      [
        8,
        19,
        null,
        34,
        46,
        null,
        null,
        null,
        null
      ]
    ]
  },
  {
    "idCarton": 1113,
    "carton": [
      [
        null,
        null,
        23,
        39,
        42,
        null,
        67,
        null,
        81
      ],
      [
        9,
        11,
        null,
        40,
        49,
        53,
        null,
        78,
        null
      ],
      [
        null,
        13,
        28,
        null,
        null,
        null,
        70,
        null,
        84
      ]
    ]
  },
  {
    "idCarton": 1114,
    "carton": [
      [
        1,
        18,
        null,
        null,
        null,
        51,
        70,
        74,
        null
      ],
      [
        null,
        19,
        24,
        39,
        42,
        null,
        null,
        80,
        null
      ],
      [
        10,
        null,
        null,
        null,
        44,
        57,
        null,
        null,
        85
      ]
    ]
  },
  {
    "idCarton": 1115,
    "carton": [
      [
        null,
        14,
        null,
        38,
        null,
        51,
        62,
        null,
        null
      ],
      [
        null,
        null,
        26,
        null,
        48,
        null,
        69,
        78,
        83
      ],
      [
        9,
        null,
        null,
        null,
        49,
        59,
        null,
        79,
        null
      ]
    ]
  },
  {
    "idCarton": 1116,
    "carton": [
      [
        1,
        null,
        null,
        null,
        null,
        56,
        65,
        null,
        83
      ],
      [
        8,
        null,
        30,
        32,
        41,
        58,
        null,
        null,
        null
      ],
      [
        null,
        12,
        null,
        35,
        46,
        null,
        68,
        80,
        null
      ]
    ]
  },
  {
    "idCarton": 1117,
    "carton": [
      [
        null,
        null,
        null,
        null,
        null,
        52,
        null,
        null,
        81
      ],
      [
        4,
        16,
        null,
        null,
        null,
        null,
        67,
        78,
        null
      ],
      [
        5,
        17,
        30,
        31,
        48,
        60,
        68,
        79,
        null
      ]
    ]
  },
  {
    "idCarton": 1118,
    "carton": [
      [
        null,
        null,
        22,
        33,
        null,
        52,
        null,
        null,
        85
      ],
      [
        null,
        18,
        null,
        null,
        43,
        59,
        65,
        71,
        null
      ],
      [
        3,
        null,
        null,
        34,
        45,
        null,
        null,
        null,
        86
      ]
    ]
  },
  {
    "idCarton": 1119,
    "carton": [
      [
        null,
        null,
        27,
        31,
        44,
        54,
        null,
        79,
        null
      ],
      [
        2,
        12,
        null,
        null,
        null,
        null,
        68,
        null,
        83
      ],
      [
        6,
        20,
        null,
        33,
        null,
        59,
        null,
        80,
        null
      ]
    ]
  },
  {
    "idCarton": 1120,
    "carton": [
      [
        null,
        13,
        null,
        31,
        null,
        52,
        null,
        null,
        81
      ],
      [
        null,
        null,
        null,
        35,
        50,
        59,
        63,
        78,
        87
      ],
      [
        1,
        null,
        28,
        null,
        null,
        null,
        69,
        null,
        null
      ]
    ]
  }
]